mccann_hub/echo_trail/__init__.py
mccann_hub/echo_trail/defaults.py
mccann_hub/echo_trail/get.py
mccann_hub/echo_trail/setup.py
mccann_hub_echo_trail-0.1.0.dist-info/licenses/LICENSE
mccann_hub_echo_trail-0.1.0.dist-info/METADATA
mccann_hub_echo_trail-0.1.0.dist-info/WHEEL
mccann_hub_echo_trail-0.1.0.dist-info/top_level.txt
mccann_hub_echo_trail-0.1.0.dist-info/RECORD
