Metadata-Version: 2.4
Name: mccann_hub-echo_trail
Version: 0.1.0
Summary: A JSON logger with metadata injection for consistent log formatting.
Author-email: Jimmy McCann <jabez007@users.noreply.github.com>
License: MIT License
Project-URL: Homepage, https://github.com/jabez007/echo_trail
Project-URL: Bug Tracker, https://github.com/jabez007/echo_trail/issues
Keywords: logging,json-logger,metadata
Classifier: Development Status :: 4 - Beta
Classifier: Intended Audience :: Developers
Classifier: Programming Language :: Python :: 3
Classifier: License :: OSI Approved :: MIT License
Requires-Python: >=3.9
License-File: LICENSE
Requires-Dist: python-json-logger>=3.0.0
Dynamic: license-file
